[
  {
    "id": "6782cfb5f951fa0b693939cb",
    "advertising_info": null,
    "alcohol_permille": 0,
    "allowed_delivery_methods": [
      "homedelivery",
      "takeaway",
      "eatin"
    ],
    "available_times": [
      {
        "days": [
          1,
          2,
          3,
          4,
          5,
          6,
          7
        ],
        "start_time": 0,
        "end_time": 86400000
      }
    ],
    "barcode_gtin": "07188209923832",
    "caffeine_info": null,
    "can_be_promoted": {
      "basket": true,
      "venue": true,
      "credits": true
    },
    "checksum": "d9ca4a86b1b05849b7e87d089ac06bb0",
    "description": "",
    "deposit": null,
    "dietary_preferences": [],
    "disabled_info": null,
    "fulfillment_lead_time": null,
    "has_extra_info": true,
    "images": [
      {
        "url": "https://imageproxy.wolt.com/assets/6888c060a3eb62eeb95663e2",
        "blurhash": "LrT8]xa#t:ocoJj[a~aypLj?Z|WE"
      }
    ],
    "is_cutlery": false,
    "is_no_contact_delivery_allowed": true,
    "is_wolt_plus_only": false,
    "lowest_price": null,
    "lowest_price_v2": null,
    "max_quantity_per_purchase": null,
    "min_quantity_per_purchase": null,
    "name": "Дәмді Тағам Пирог С Курицей",
    "options": [],
    "original_price": null,
    "item_price_discount_validity_period": null,
    "price": 200000,
    "product_hierarchy_tags": [
      "PERISHABLE"
    ],
    "purchasable_balance": 1,
    "restrictions": [],
    "return_policy": null,
    "sell_by_weight_config": null,
    "should_display_purchasable_balance": true,
    "tags": [],
    "unit_info": "640 г",
    "unit_price": {
      "base": 1,
      "original_price": null,
      "price": 312500,
      "unit": "kilogram"
    },
    "variant": null,
    "vat_category_code": null,
    "vat_percentage": 0,
    "vat_percentage_decimal": null,
    "external_compliance_link": null,
    "consent_info": {
      "ask_consent": false,
      "blur_image": false
    },
    "categories": [
      "Мясо и птица",
      "Птица"
    ]
  },
  {
    "id": "3419d003bffc7138a8780f62",
    "advertising_info": null,
    "alcohol_permille": 0,
    "allowed_delivery_methods": [
      "homedelivery",
      "takeaway",
      "eatin"
    ],
    "available_times": [
      {
        "days": [
          1,
          2,
          3,
          4,
          5,
          6,
          7
        ],
        "start_time": 0,
        "end_time": 86400000
      }
    ],
    "barcode_gtin": "04605025053237",
    "caffeine_info": null,
    "can_be_promoted": {
      "basket": true,
      "venue": true,
      "credits": true
    },
    "checksum": "cbe9e979a074386d4034ca06b5e50ee6",
    "description": "",
    "deposit": null,
    "dietary_preferences": [],
    "disabled_info": null,
    "fulfillment_lead_time": null,
    "has_extra_info": true,
    "images": [
      {
        "url": "https://imageproxy.wolt.com/assets/688b98fca3eb62eeb95c2100",
        "blurhash": "L-PQEUjs~pW?azWroeslkXjZi_bH"
      }
    ],
    "is_cutlery": false,
    "is_no_contact_delivery_allowed": true,
    "is_wolt_plus_only": false,
    "lowest_price": null,
    "lowest_price_v2": null,
    "max_quantity_per_purchase": null,
    "min_quantity_per_purchase": null,
    "name": "Пава-Пава Филе Бедра Индейки Замороженное 800 Г",
    "options": [],
    "original_price": null,
    "item_price_discount_validity_period": null,
    "price": 465000,
    "product_hierarchy_tags": [
      "UNKNOWN"
    ],
    "purchasable_balance": 10,
    "restrictions": [],
    "return_policy": null,
    "sell_by_weight_config": null,
    "should_display_purchasable_balance": false,
    "tags": [],
    "unit_info": "800 г",
    "unit_price": {
      "base": 1,
      "original_price": null,
      "price": 581250,
      "unit": "kilogram"
    },
    "variant": null,
    "vat_category_code": null,
    "vat_percentage": 12,
    "vat_percentage_decimal": "12.0",
    "external_compliance_link": null,
    "consent_info": {
      "ask_consent": false,
      "blur_image": false
    },
    "categories": [
      "Мясо и птица",
      "Птица"
    ]
  },
  {
    "id": "5c5970f22ae78a7e3358338c",
    "advertising_info": null,
    "alcohol_permille": 0,
    "allowed_delivery_methods": [
      "homedelivery",
      "takeaway",
      "eatin"
    ],
    "available_times": [
      {
        "days": [
          1,
          2,
          3,
          4,
          5,
          6,
          7
        ],
        "start_time": 0,
        "end_time": 86400000
      }
    ],
    "barcode_gtin": "04605025053220",
    "caffeine_info": null,
    "can_be_promoted": {
      "basket": true,
      "venue": true,
      "credits": true
    },
    "checksum": "df58f2d3e5ae82879f85fc722cd11265",
    "description": "",
    "deposit": null,
    "dietary_preferences": [],
    "disabled_info": null,
    "fulfillment_lead_time": null,
    "has_extra_info": true,
    "images": [
      {
        "url": "https://imageproxy.wolt.com/assets/688b98faa3eb62eeb95c20de",
        "blurhash": "LwQTDqj[~Va#sSa#W=oJbvazi_oL"
      }
    ],
    "is_cutlery": false,
    "is_no_contact_delivery_allowed": true,
    "is_wolt_plus_only": false,
    "lowest_price": null,
    "lowest_price_v2": null,
    "max_quantity_per_purchase": null,
    "min_quantity_per_purchase": null,
    "name": "Пава-Пава Филе Грудки Индейки Большое 800 Г",
    "options": [],
    "original_price": null,
    "item_price_discount_validity_period": null,
    "price": 465000,
    "product_hierarchy_tags": [
      "UNKNOWN"
    ],
    "purchasable_balance": 26,
    "restrictions": [],
    "return_policy": null,
    "sell_by_weight_config": null,
    "should_display_purchasable_balance": false,
    "tags": [],
    "unit_info": "800 г",
    "unit_price": {
      "base": 1,
      "original_price": null,
      "price": 581250,
      "unit": "kilogram"
    },
    "variant": null,
    "vat_category_code": null,
    "vat_percentage": 12,
    "vat_percentage_decimal": "12.0",
    "external_compliance_link": null,
    "consent_info": {
      "ask_consent": false,
      "blur_image": false
    },
    "categories": [
      "Мясо и птица",
      "Птица"
    ]
  }
]